aws_ddk_core/__init__.py
aws_ddk_core/py.typed
aws_ddk_core/_jsii/__init__.py
aws_ddk_core/_jsii/aws-ddk-core@1.4.1.jsii.tgz
aws_ddk_core-1.4.1.dist-info/LICENSE
aws_ddk_core-1.4.1.dist-info/METADATA
aws_ddk_core-1.4.1.dist-info/NOTICE
aws_ddk_core-1.4.1.dist-info/WHEEL
aws_ddk_core-1.4.1.dist-info/top_level.txt
aws_ddk_core-1.4.1.dist-info/RECORD
