Metadata-Version: 2.1
Name: aws-ddk-core
Version: 1.4.1
Summary: The AWS DataOps Development Kit is an open source development framework for customers that build data workflows and modern data architecture on AWS.
Home-page: https://github.com/awslabs/aws-ddk/tree/main
Author: AWS Professional Services<aws-proserve-orion-dev@amazon.com>
License: Apache-2.0
Project-URL: Source, https://github.com/awslabs/aws-ddk/tree/main
Classifier: Intended Audience :: Developers
Classifier: Operating System :: OS Independent
Classifier: Programming Language :: JavaScript
Classifier: Programming Language :: Python :: 3 :: Only
Classifier: Programming Language :: Python :: 3.8
Classifier: Programming Language :: Python :: 3.9
Classifier: Programming Language :: Python :: 3.10
Classifier: Programming Language :: Python :: 3.11
Classifier: Typing :: Typed
Classifier: Development Status :: 5 - Production/Stable
Classifier: License :: OSI Approved
Requires-Python: ~=3.8
License-File: LICENSE
License-File: NOTICE
Requires-Dist: aws-cdk-lib<3.0.0,>=2.177.0
Requires-Dist: aws-cdk.aws-glue-alpha<3.0.0,>=2.177.0.a0
Requires-Dist: aws-cdk.aws-kinesisfirehose-alpha<3.0.0,>=2.177.0.a0
Requires-Dist: aws-cdk.aws-kinesisfirehose-destinations-alpha<3.0.0,>=2.177.0.a0
Requires-Dist: aws-cdk.integ-tests-alpha<3.0.0,>=2.177.0.a0
Requires-Dist: constructs<11.0.0,>=10.0.5
Requires-Dist: jsii<2.0.0,>=1.105.0
Requires-Dist: publication>=0.0.3
Requires-Dist: typeguard<4.3.0,>=2.13.3
